evomap/__init__.py
evomap/datasets.py
evomap/metrics.py
evomap/preprocessing.py
evomap/printer.py
evomap/transform.py
evomap/data/__init__.py
evomap/data/cars/__init__.py
evomap/data/cars/customer_preference_ratings.csv
evomap/data/cars/perceptual_attribute_ratings.csv
evomap/data/cars/perceptual_attribute_ratings.xlsx
evomap/data/tnic_sample_small/__init__.py
evomap/data/tnic_sample_small/tnic_sample_small.csv
evomap/data/tnic_sample_small/tnic_sample_small_old.csv
evomap/data/tnic_sample_tech/__init__.py
evomap/data/tnic_sample_tech/tnic_sample_technology.csv
evomap/data/tnic_sample_tech/tnic_sample_technology_with_netflix.csv
evomap/data/tnic_snapshot/__init__.py
evomap/data/tnic_snapshot/cluster.npy
evomap/data/tnic_snapshot/label.npy
evomap/data/tnic_snapshot/sim_mat.npy
evomap/data/tnic_snapshot/size.npy
evomap/data/tnic_snapshot_small/__init__.py
evomap/data/tnic_snapshot_small/cluster.npy
evomap/data/tnic_snapshot_small/labels.npy
evomap/data/tnic_snapshot_small/sim_mat.npy
evomap/mapping/__init__.py
evomap/mapping/_cmds.py
evomap/mapping/_mds.py
evomap/mapping/_optim.py
evomap/mapping/_regression.py
evomap/mapping/_sammon.py
evomap/mapping/_tsne.py
evomap/mapping/evomap/__init__.py
evomap/mapping/evomap/_core.py
evomap/mapping/evomap/_evomds.py
evomap/mapping/evomap/_evosammon.py
evomap/mapping/evomap/_evotsne.py
evomap/mapping/evomap/_utils.py
evomap-0.5.1.dist-info/licenses/LICENSE
evomap-0.5.1.dist-info/METADATA
evomap-0.5.1.dist-info/WHEEL
evomap-0.5.1.dist-info/top_level.txt
evomap-0.5.1.dist-info/RECORD
