Metadata-Version: 2.4
Name: evomap
Version: 0.5.1
Summary: A Python Toolbox for Mapping Evolving Relationship Data
Home-page: https://github.com/mpmatthe/evomap
Author: Maximilian Matthe, Daniel M. Ringel, Bernd Skiera
Author-email: mpmatthe@iu.edu
License: MIT
Keywords: mapping,data analysis,network analysis,evolving relationship data,temporal networks
Classifier: Development Status :: 4 - Beta
Classifier: Intended Audience :: Science/Research
Classifier: License :: OSI Approved :: MIT License
Classifier: Operating System :: POSIX
Classifier: Operating System :: MacOS
Classifier: Programming Language :: Python :: 3.10
Classifier: Programming Language :: Python :: 3.11
Requires-Python: >=3.9
License-File: LICENSE
Requires-Dist: cycler
Requires-Dist: matplotlib
Requires-Dist: scipy<=1.15.3
Requires-Dist: numba
Requires-Dist: numpy
Requires-Dist: pandas
Requires-Dist: scikit-learn
Requires-Dist: scikit-optimize
Requires-Dist: seaborn
Requires-Dist: statsmodels
Dynamic: author
Dynamic: author-email
Dynamic: classifier
Dynamic: description
Dynamic: description-content-type
Dynamic: home-page
Dynamic: keywords
Dynamic: license
Dynamic: license-file
Dynamic: requires-dist
Dynamic: requires-python
Dynamic: summary
